<?xml version="1.0" encoding="UTF-8"?>
<!DOCTYPE sqlMap PUBLIC "-//iBATIS.com//DTD SQL Map 2.0//EN"
        "http://ibatis.apache.org/dtd/sql-map-2.dtd">

<sqlMap namespace="eventsInfo">
	<typeAlias alias="eventsInfo" type="com.szrj.business.model.event.EventsInfo"/>
	
	<select id="search_count" parameterClass="eventsInfo" resultClass="Integer">
		select count(*)
		from e_eventsinfo_t
		where validflag>0 and cdtid=$cdtid$
		<isNotEqual prepend="AND" property="workinfoid" compareValue="0">
			workinfoid = #workinfoid#
		</isNotEqual>
	</select>
	<select id="search" parameterClass="eventsInfo" resultClass="eventsInfo">
		select *
		from e_eventsinfo_t
		where validflag>0 and cdtid=$cdtid$
		<isNotEqual prepend="AND" property="workinfoid" compareValue="0">
			workinfoid = #workinfoid#
		</isNotEqual>
		order by fssj desc
	</select>
	
	<!-- 综合查询 -->
	<select id="searchSynthetic_count" parameterClass="eventsInfo" resultClass="Integer">
		select count(*)
		from e_eventsinfo_t ev
		LEFT JOIN e_contradictioninfo_t ct
		on ev.cdtid=ct.id
		where ev.validflag>0 and ct.validflag>0
		<isNotEmpty prepend="AND" property="cdtlevel">
			ct.cdtlevel like '%$cdtlevel$%'
		</isNotEmpty>
		<isNotEmpty prepend="AND" property="cdtname">
			ct.cdtname like '%$cdtname$%'
		</isNotEmpty>
		<isNotEmpty prepend="AND" property="sql">
			($sql$)
		</isNotEmpty>
		<isNotEmpty prepend="AND" property="etitle">
			ev.etitle like '%$etitle$%'
		</isNotEmpty>
		<isNotEmpty prepend="AND" property="sjgk">
			ev.sjgk like '%$sjgk$%'
		</isNotEmpty>
		<isNotEmpty prepend="AND" property="sfbwd">
			ev.sfbwd like '%$sfbwd$%'
		</isNotEmpty>
		<isNotEmpty prepend="AND" property="xwfs">
			ev.xwfs like '%$xwfs$%'
		</isNotEmpty>
	</select>
	<select id="searchSynthetic" parameterClass="eventsInfo" resultClass="eventsInfo">
		select ev.*,GROUP_CONCAT(bm.basicName order by bm.id) as cdttypename,ct.cdtname,ct.cdtlevel
		from e_eventsinfo_t ev
		LEFT JOIN e_contradictioninfo_t ct
		on ev.cdtid=ct.id
		LEFT JOIN sys_basic_msg_t bm   
		on FIND_IN_SET(bm.id,ct.cdttype)
		where ev.validflag>0 and ct.validflag>0
		<isNotEmpty prepend="AND" property="cdtlevel">
			ct.cdtlevel like '%$cdtlevel$%'
		</isNotEmpty>
		<isNotEmpty prepend="AND" property="cdtname">
			ct.cdtname like '%$cdtname$%'
		</isNotEmpty>
		<isNotEmpty prepend="AND" property="sql">
			($sql$)
		</isNotEmpty>
		<isNotEmpty prepend="AND" property="etitle">
			ev.etitle like '%$etitle$%'
		</isNotEmpty>
		<isNotEmpty prepend="AND" property="sjgk">
			ev.sjgk like '%$sjgk$%'
		</isNotEmpty>
		<isNotEmpty prepend="AND" property="sfbwd">
			ev.sfbwd like '%$sfbwd$%'
		</isNotEmpty>
		<isNotEmpty prepend="AND" property="xwfs">
			ev.xwfs like '%$xwfs$%'
		</isNotEmpty>
		GROUP BY ev.id
	</select>
	
	<!-- 新增 -->
	<insert id="add" parameterClass="eventsInfo">
		INSERT INTO e_eventsinfo_t
		(cdtid,etitle,fxdj,sjgk,sfbwd,fssj,ssrs,sfgm,xwfs,xcczjg,validflag,addoperatorid,addoperator,addtime,memo,workinfoid,attachments)
		VALUES
		($cdtid$,'$etitle$','$fxdj$','$sjgk$','$sfbwd$','$fssj$','$ssrs$','$sfgm$','$xwfs$','$xcczjg$',$validflag$,$addoperatorid$,'$addoperator$','$addtime$','$memo$',$workinfoid$,'$attachments$')
		<selectKey resultClass="Integer" keyProperty="id">SELECT LAST_INSERT_ID() AS ID</selectKey>
	</insert>
	<!-- 删除 -->
	<update id="cancel" parameterClass="eventsInfo">
		UPDATE e_eventsinfo_t
		SET validflag = 0,updateoperator='$updateoperator$',updatetime='$updatetime$'
		WHERE id = $id$
	</update>
	<!-- 修改 -->
	<update id="update" parameterClass="eventsInfo">
		UPDATE e_eventsinfo_t
		SET etitle='$etitle$',fxdj='$fxdj$',sjgk='$sjgk$',sfbwd='$sfbwd$',fssj='$fssj$',ssrs='$ssrs$',sfgm='$sfgm$',xwfs='$xwfs$',xcczjg='$xcczjg$',
		updateoperator='$updateoperator$',updatetime='$updatetime$',memo='$memo$',attachments='$attachments$'
		WHERE id = $id$
	</update>
	<!-- 根据ID获取 -->
	<select id="getById" parameterClass="int" resultClass="eventsInfo">
		select A.*,GROUP_CONCAT(sf.fileName order by sf.id) as filenames,GROUP_CONCAT(sf.id order by sf.id) as fileids
		from(SELECT *   FROM e_eventsinfo_t   
		WHERE validflag > 0 AND id = $id$)A
		LEFT JOIN sys_file_t sf on FIND_IN_SET(sf.id,A.attachments)
		GROUP BY A.id
	</select>
	
	<select id="countEventByWorkinfoid" parameterClass="eventsInfo" resultClass="int">
		select count(*)
		from e_eventsinfo_t
		where validflag>0 and workinfoid = $workinfoid$
	</select>
	
	<!-- 政法委 -->
	<select id="search_count_zfw" parameterClass="eventsInfo" resultClass="Integer">
		select count(*)
		from zfw_e_eventsinfo_t
		where validflag>0 and cdtid=$cdtid$
		<isNotEqual prepend="AND" property="workinfoid" compareValue="0">
			workinfoid = #workinfoid#
		</isNotEqual>
	</select>
	<select id="search_zfw" parameterClass="eventsInfo" resultClass="eventsInfo">
		select *
		from zfw_e_eventsinfo_t
		where validflag>0 and cdtid=$cdtid$
		<isNotEqual prepend="AND" property="workinfoid" compareValue="0">
			workinfoid = #workinfoid#
		</isNotEqual>
		order by fssj desc
	</select>
	
	<select id="getById_zfw" parameterClass="int" resultClass="eventsInfo">
		select A.*,GROUP_CONCAT(sf.fileName order by sf.id) as filenames,GROUP_CONCAT(sf.id order by sf.id) as fileids
		from(SELECT *   FROM zfw_e_eventsinfo_t   
		WHERE validflag > 0 AND id = $id$)A
		LEFT JOIN zfw_sys_file_t sf on FIND_IN_SET(sf.id,A.attachments)
		GROUP BY A.id
	</select>
	
	<update id="update_zfw" parameterClass="int">
		UPDATE zfw_e_eventsinfo_t
		SET validflag = $validflag$
		WHERE id = $id$
	</update>
</sqlMap>